<?xml version="1.0" encoding="utf-8" ?><dwsync><file name="CommunityLearningController.php" server="192.168.0.160" local="3788348465" remote="3744657000" Dst="-1" /><file name="BackgroundProcessController.php" server="192.168.0.160" local="3788348465" remote="3754047060" Dst="-1" /><file name="CoursesDetailController.php" server="192.168.0.160" local="3788348465" remote="3744657000" Dst="-1" /><file name="CoursesController.php" server="192.168.0.160" local="3788348465" remote="3744657000" Dst="-1" /><file name="CoursesHookViewController.php" server="192.168.0.160" local="3788348465" remote="3758278860" Dst="-1" /><file name="CourseShowController.php" server="192.168.0.160" local="3788348465" remote="3757933200" Dst="-1" /><file name="CoursesPreferencesController.php" server="192.168.0.160" local="3788348465" remote="3744657000" Dst="-1" /><file name="EditProfileController.php" server="192.168.0.160" local="3788348465" remote="3744657000" Dst="-1" /><file name="CoursesRegisterController.php" server="192.168.0.160" local="3788348465" remote="3744669660" Dst="-1" /><file name="IncomingEventsController.php" server="192.168.0.160" local="3788348465" remote="3744657000" Dst="-1" /><file name="LifeTimeController.php" server="192.168.0.160" local="3788348465" remote="3744657000" Dst="-1" /><file name="MeetingsCreationController.php" server="192.168.0.160" local="3788348465" remote="3744657000" Dst="-1" /><file name="MeetingsRegistrationController.php" server="192.168.0.160" local="3788348465" remote="3744657000" Dst="-1" /><file name="MeetingsViewController.php" server="192.168.0.160" local="3788348466" remote="3744657000" Dst="-1" /><file name="MtsController.php" server="192.168.0.160" local="3788354803" remote="3788354760" Dst="-1" /><file name="PrivacyPageController.php" server="192.168.0.160" local="3788348466" remote="3744657000" Dst="-1" /><file name="PastEventsController.php" server="192.168.0.160" local="3788348466" remote="3744657000" Dst="-1" /><file name="ResourcesCategoriesController.php" server="192.168.0.160" local="3788348466" remote="3744657000" Dst="-1" /><file name="ProfileController.php" server="192.168.0.160" local="3788348466" remote="3754677420" Dst="-1" /><file name="ResourcesSearchController.php" server="192.168.0.160" local="3788348466" remote="3744657000" Dst="-1" /><file name="ResourcesCategoriesViewController.php" server="192.168.0.160" local="3788348466" remote="3744657000" Dst="-1" /><file name="ResourcesSubcategoriesViewController.php" server="192.168.0.160" local="3788348466" remote="3744657000" Dst="-1" /><file name="ResultadoBusquedaEncuentrosController.php" server="192.168.0.160" local="3788348466" remote="3744657000" Dst="-1" /><file name="ResultadoBusquedaRecursosController.php" server="192.168.0.160" local="3788348466" remote="3744657000" Dst="-1" /><file name="ResultadoBusquedaMemoriasController.php" server="192.168.0.160" local="3788348466" remote="3744657000" Dst="-1" /><file name="ResultadoBusquedaTemasController.php" server="192.168.0.160" local="3788348466" remote="3744657000" Dst="-1" /><file name="UniqueChallengesController.php" server="192.168.0.160" local="3788348466" remote="3744657000" Dst="-1" /><file name="UpdateProfileController.php" server="192.168.0.160" local="3788348466" remote="3744657000" Dst="-1" /><file name="MtsController.php" server="192.168.0.160//inetpub/wwwroot/icbf/" local="3788374631" remote="3788374633" Dst="-1" /></dwsync>